LICENSE
README.md
pyproject.toml
setup.py
padertorch/__init__.py
padertorch/base.py
padertorch/configurable.py
padertorch/io.py
padertorch/utils.py
padertorch.egg-info/PKG-INFO
padertorch.egg-info/SOURCES.txt
padertorch.egg-info/dependency_links.txt
padertorch.egg-info/requires.txt
padertorch.egg-info/top_level.txt
padertorch/contrib/__init__.py
padertorch/contrib/cb/__init__.py
padertorch/contrib/cb/array.py
padertorch/contrib/cb/complex.py
padertorch/contrib/cb/data.py
padertorch/contrib/cb/feature_extractor.py
padertorch/contrib/cb/hooks.py
padertorch/contrib/cb/io.py
padertorch/contrib/cb/summary.py
padertorch/contrib/cb/tensorboard_symlink_tree.py
padertorch/contrib/cb/track.py
padertorch/contrib/cb/transform.py
padertorch/contrib/data/__init__.py
padertorch/contrib/data/utils.py
padertorch/contrib/data/wsj0_mix/__init__.py
padertorch/contrib/data/wsj0_mix/create_json.py
padertorch/contrib/examples/__init__.py
padertorch/contrib/examples/sound_recognition/__init__.py
padertorch/contrib/examples/sound_recognition/audio_tagging/__init__.py
padertorch/contrib/examples/sound_recognition/audio_tagging/data.py
padertorch/contrib/examples/sound_recognition/audio_tagging/evaluate.py
padertorch/contrib/examples/sound_recognition/audio_tagging/model.py
padertorch/contrib/examples/sound_recognition/audio_tagging/train.py
padertorch/contrib/examples/source_separation/__init__.py
padertorch/contrib/examples/source_separation/or_pit/__init__.py
padertorch/contrib/examples/source_separation/or_pit/evaluate.py
padertorch/contrib/examples/source_separation/or_pit/model.py
padertorch/contrib/examples/source_separation/or_pit/templates.py
padertorch/contrib/examples/source_separation/or_pit/train.py
padertorch/contrib/examples/source_separation/pit/__init__.py
padertorch/contrib/examples/source_separation/pit/data.py
padertorch/contrib/examples/source_separation/pit/evaluate.py
padertorch/contrib/examples/source_separation/pit/model.py
padertorch/contrib/examples/source_separation/pit/templates.py
padertorch/contrib/examples/source_separation/pit/train.py
padertorch/contrib/examples/source_separation/tasnet/__init__.py
