Metadata-Version: 2.1
Name: padertorch
Version: 0.0.1
Summary: A collection of common functionality to simplify the design, training and evaluation of machine learning models based on pytorch with an emphasis on speech processing.
Home-page: https://github.com/fgnt/padertorch/
Author: Department of Communications Engineering, Paderborn University
Author-email: sek@nt.upb.de
License: MIT
Keywords: pytorch,audio,speech
Classifier: Development Status :: 3 - Alpha
Classifier: Intended Audience :: Developers
Classifier: Topic :: Software Development :: Build Tools
Classifier: License :: OSI Approved :: MIT License
Classifier: Programming Language :: Python :: 3.10
License-File: LICENSE
Requires-Dist: torch
Requires-Dist: tensorboardX
Requires-Dist: einops
Requires-Dist: tqdm
Requires-Dist: natsort
Requires-Dist: lazy_dataset
Requires-Dist: IPython
Requires-Dist: paderbox
Provides-Extra: test
Requires-Dist: pytest; extra == "test"
Requires-Dist: pytest-cov; extra == "test"
Requires-Dist: mock; extra == "test"
Requires-Dist: coverage; extra == "test"
Requires-Dist: pylint; extra == "test"
Requires-Dist: sacred; extra == "test"
Requires-Dist: appdirs; extra == "test"
Requires-Dist: protobuf3_to_dict; extra == "test"
Requires-Dist: torchvision; extra == "test"
Requires-Dist: matplotlib; extra == "test"
Requires-Dist: torch_complex; extra == "test"
Requires-Dist: pyyaml; extra == "test"
Requires-Dist: humanize; extra == "test"
Requires-Dist: codecarbon; extra == "test"
Provides-Extra: all
Requires-Dist: pytest; extra == "all"
Requires-Dist: pytest-cov; extra == "all"
Requires-Dist: mock; extra == "all"
Requires-Dist: coverage; extra == "all"
Requires-Dist: pylint; extra == "all"
Requires-Dist: sacred; extra == "all"
Requires-Dist: appdirs; extra == "all"
Requires-Dist: protobuf3_to_dict; extra == "all"
Requires-Dist: torchvision; extra == "all"
Requires-Dist: matplotlib; extra == "all"
Requires-Dist: torch_complex; extra == "all"
Requires-Dist: pyyaml; extra == "all"
Requires-Dist: humanize; extra == "all"
Requires-Dist: codecarbon; extra == "all"
